refactor_utils/__init__.py
refactor_utils/cli.py
refactor_utils/core.py
refactor_utils/movers.py
refactor_utils/options.py
refactor_utils/utils.py
refactor_utils-3.1.7.dist-info/licenses/LICENSE
refactor_utils-3.1.7.dist-info/METADATA
refactor_utils-3.1.7.dist-info/WHEEL
refactor_utils-3.1.7.dist-info/entry_points.txt
refactor_utils-3.1.7.dist-info/top_level.txt
refactor_utils-3.1.7.dist-info/RECORD
