Metadata-Version: 2.4
Name: refactor_utils
Version: 3.1.7
Summary: Utilities to refactor small python packages: extract funcs/constants/classes into modules
Author-email: you <you@example.com>
Requires-Python: >=3.8
License-File: LICENSE
Dynamic: license-file
